{
  "hash": "d222fb58",
  "configHash": "5d16408f",
  "lockfileHash": "2283a16b",
  "browserHash": "2c84e275",
  "optimized": {
    "react": {
      "src": "../../node_modules/react/index.js",
      "file": "react.js",
      "fileHash": "d759c74d",
      "needsInterop": true
    },
    "react-dom/client": {
      "src": "../../node_modules/react-dom/client.js",
      "file": "react-dom_client.js",
      "fileHash": "c08ce701",
      "needsInterop": true
    },
    "react-router": {
      "src": "../../node_modules/react-router/dist/development/index.mjs",
      "file": "react-router.js",
      "fileHash": "12a67549",
      "needsInterop": false
    },
    "chart.js": {
      "src": "../../node_modules/chart.js/dist/chart.js",
      "file": "chart__js.js",
      "fileHash": "e234ef75",
      "needsInterop": false
    }
  },
  "chunks": {
    "chunk-3527N3GG": {
      "file": "chunk-3527N3GG.js"
    },
    "chunk-EQCVQC35": {
      "file": "chunk-EQCVQC35.js"
    }
  }
}